{
  "cunli": "壽豐鄉_月眉村",
  "total_records": 1,
  "sum_fields": {
    "agree_votes": 47,
    "disagree_votes": 81,
    "valid_votes": 128,
    "invalid_votes": 1,
    "total_voters": 129,
    "ballots_not_cast": 0,
    "ballots_issued": 129,
    "unused_ballots": 91,
    "eligible_voters": 220,
    "average_turnout_rate": 58.64
  },
  "records": [
    {
      "recall_case": "第11屆立法委員(花蓮縣選舉區)傅崐萁罷免案各投開票所投開票結果表",
      "district": "壽豐鄉",
      "village": "月眉村",
      "polling_station": "226",
      "agree_votes": 47,
      "disagree_votes": 81,
      "valid_votes": 128,
      "invalid_votes": 1,
      "total_voters": 129,
      "ballots_not_cast": 0,
      "ballots_issued": 129,
      "unused_ballots": 91,
      "eligible_voters": 220,
      "turnout_rate": 58.64
    }
  ],
  "VILLCODE": "10015060013",
  "COUNTYCODE": "10015",
  "TOWNCODE": "10015060",
  "COUNTYNAME": "花蓮縣",
  "TOWNNAME": "壽豐鄉",
  "VILLNAME": "月眉村"
}