{
  "cunli": "七堵區_瑪南里",
  "total_records": 1,
  "sum_fields": {
    "agree_votes": 92,
    "disagree_votes": 81,
    "valid_votes": 173,
    "invalid_votes": 1,
    "total_voters": 174,
    "ballots_not_cast": 0,
    "ballots_issued": 174,
    "unused_ballots": 183,
    "eligible_voters": 357,
    "average_turnout_rate": 48.74
  },
  "records": [
    {
      "recall_case": "第11屆立法委員(基隆市選舉區)林沛祥罷免案各投開票所投開票結果表",
      "district": "七堵區",
      "village": "瑪南里",
      "polling_station": "278",
      "agree_votes": 92,
      "disagree_votes": 81,
      "valid_votes": 173,
      "invalid_votes": 1,
      "total_voters": 174,
      "ballots_not_cast": 0,
      "ballots_issued": 174,
      "unused_ballots": 183,
      "eligible_voters": 357,
      "turnout_rate": 48.74
    }
  ],
  "VILLCODE": "10017020012",
  "COUNTYCODE": "10017",
  "TOWNCODE": "10017020",
  "COUNTYNAME": "基隆市",
  "TOWNNAME": "七堵區",
  "VILLNAME": "瑪南里"
}