{
  "cunli": "北區_新雅里",
  "total_records": 8,
  "sum_fields": {
    "agree_votes": 2275,
    "disagree_votes": 2693,
    "valid_votes": 4968,
    "invalid_votes": 38,
    "total_voters": 5006,
    "ballots_not_cast": 0,
    "ballots_issued": 5006,
    "unused_ballots": 3645,
    "eligible_voters": 8651,
    "average_turnout_rate": 57.87
  },
  "records": [
    {
      "recall_case": "第11屆立法委員(新竹市選舉區)鄭正鈐罷免案各投開票所投開票結果表",
      "district": "北區",
      "village": "新雅里",
      "polling_station": "216",
      "agree_votes": 307,
      "disagree_votes": 387,
      "valid_votes": 694,
      "invalid_votes": 1,
      "total_voters": 695,
      "ballots_not_cast": 0,
      "ballots_issued": 695,
      "unused_ballots": 536,
      "eligible_voters": 1231,
      "turnout_rate": 56.46
    },
    {
      "recall_case": "第11屆立法委員(新竹市選舉區)鄭正鈐罷免案各投開票所投開票結果表",
      "district": "北區",
      "village": "新雅里",
      "polling_station": "217",
      "agree_votes": 268,
      "disagree_votes": 328,
      "valid_votes": 596,
      "invalid_votes": 4,
      "total_voters": 600,
      "ballots_not_cast": 0,
      "ballots_issued": 600,
      "unused_ballots": 409,
      "eligible_voters": 1009,
      "turnout_rate": 59.46
    },
    {
      "recall_case": "第11屆立法委員(新竹市選舉區)鄭正鈐罷免案各投開票所投開票結果表",
      "district": "北區",
      "village": "新雅里",
      "polling_station": "218",
      "agree_votes": 294,
      "disagree_votes": 294,
      "valid_votes": 588,
      "invalid_votes": 11,
      "total_voters": 599,
      "ballots_not_cast": 0,
      "ballots_issued": 599,
      "unused_ballots": 446,
      "eligible_voters": 1045,
      "turnout_rate": 57.32
    },
    {
      "recall_case": "第11屆立法委員(新竹市選舉區)鄭正鈐罷免案各投開票所投開票結果表",
      "district": "北區",
      "village": "新雅里",
      "polling_station": "219",
      "agree_votes": 284,
      "disagree_votes": 314,
      "valid_votes": 598,
      "invalid_votes": 6,
      "total_voters": 604,
      "ballots_not_cast": 0,
      "ballots_issued": 604,
      "unused_ballots": 423,
      "eligible_voters": 1027,
      "turnout_rate": 58.81
    },
    {
      "recall_case": "新竹市第11屆市長高虹安罷免案在新竹市各投開票所投開票結果表",
      "district": "北區",
      "village": "新雅里",
      "polling_station": "216",
      "agree_votes": 302,
      "disagree_votes": 393,
      "valid_votes": 695,
      "invalid_votes": 2,
      "total_voters": 697,
      "ballots_not_cast": 0,
      "ballots_issued": 697,
      "unused_ballots": 539,
      "eligible_voters": 1236,
      "turnout_rate": 56.39
    },
    {
      "recall_case": "新竹市第11屆市長高虹安罷免案在新竹市各投開票所投開票結果表",
      "district": "北區",
      "village": "新雅里",
      "polling_station": "217",
      "agree_votes": 257,
      "disagree_votes": 343,
      "valid_votes": 600,
      "invalid_votes": 4,
      "total_voters": 604,
      "ballots_not_cast": 0,
      "ballots_issued": 604,
      "unused_ballots": 416,
      "eligible_voters": 1020,
      "turnout_rate": 59.22
    },
    {
      "recall_case": "新竹市第11屆市長高虹安罷免案在新竹市各投開票所投開票結果表",
      "district": "北區",
      "village": "新雅里",
      "polling_station": "218",
      "agree_votes": 286,
      "disagree_votes": 310,
      "valid_votes": 596,
      "invalid_votes": 6,
      "total_voters": 602,
      "ballots_not_cast": 0,
      "ballots_issued": 602,
      "unused_ballots": 450,
      "eligible_voters": 1052,
      "turnout_rate": 57.22
    },
    {
      "recall_case": "新竹市第11屆市長高虹安罷免案在新竹市各投開票所投開票結果表",
      "district": "北區",
      "village": "新雅里",
      "polling_station": "219",
      "agree_votes": 277,
      "disagree_votes": 324,
      "valid_votes": 601,
      "invalid_votes": 4,
      "total_voters": 605,
      "ballots_not_cast": 0,
      "ballots_issued": 605,
      "unused_ballots": 426,
      "eligible_voters": 1031,
      "turnout_rate": 58.68
    }
  ],
  "VILLCODE": "10018020038",
  "COUNTYCODE": "10018",
  "TOWNCODE": "10018020",
  "COUNTYNAME": "新竹市",
  "TOWNNAME": "北區",
  "VILLNAME": "新雅里"
}