{
  "cunli": "板橋區_玉光里",
  "total_records": 3,
  "sum_fields": {
    "agree_votes": 1253,
    "disagree_votes": 1243,
    "valid_votes": 2496,
    "invalid_votes": 12,
    "total_voters": 2508,
    "ballots_not_cast": 0,
    "ballots_issued": 2508,
    "unused_ballots": 2099,
    "eligible_voters": 4607,
    "average_turnout_rate": 54.44
  },
  "records": [
    {
      "recall_case": "第11屆立法委員(新北市第7選舉區)葉元之罷免案各投開票所投開票結果表",
      "district": "板橋區",
      "village": "玉光里",
      "polling_station": "340",
      "agree_votes": 372,
      "disagree_votes": 401,
      "valid_votes": 773,
      "invalid_votes": 5,
      "total_voters": 778,
      "ballots_not_cast": 0,
      "ballots_issued": 778,
      "unused_ballots": 679,
      "eligible_voters": 1457,
      "turnout_rate": 53.4
    },
    {
      "recall_case": "第11屆立法委員(新北市第7選舉區)葉元之罷免案各投開票所投開票結果表",
      "district": "板橋區",
      "village": "玉光里",
      "polling_station": "341",
      "agree_votes": 442,
      "disagree_votes": 400,
      "valid_votes": 842,
      "invalid_votes": 3,
      "total_voters": 845,
      "ballots_not_cast": 0,
      "ballots_issued": 845,
      "unused_ballots": 702,
      "eligible_voters": 1547,
      "turnout_rate": 54.62
    },
    {
      "recall_case": "第11屆立法委員(新北市第7選舉區)葉元之罷免案各投開票所投開票結果表",
      "district": "板橋區",
      "village": "玉光里",
      "polling_station": "342",
      "agree_votes": 439,
      "disagree_votes": 442,
      "valid_votes": 881,
      "invalid_votes": 4,
      "total_voters": 885,
      "ballots_not_cast": 0,
      "ballots_issued": 885,
      "unused_ballots": 718,
      "eligible_voters": 1603,
      "turnout_rate": 55.21
    }
  ],
  "VILLCODE": "65000010059",
  "COUNTYCODE": "65000",
  "TOWNCODE": "65000010",
  "COUNTYNAME": "新北市",
  "TOWNNAME": "板橋區",
  "VILLNAME": "玉光里"
}