{
  "cunli": "東區_豐功里",
  "total_records": 8,
  "sum_fields": {
    "agree_votes": 1997,
    "disagree_votes": 3187,
    "valid_votes": 5184,
    "invalid_votes": 33,
    "total_voters": 5217,
    "ballots_not_cast": 0,
    "ballots_issued": 5217,
    "unused_ballots": 3307,
    "eligible_voters": 8524,
    "average_turnout_rate": 61.2
  },
  "records": [
    {
      "recall_case": "第11屆立法委員(新竹市選舉區)鄭正鈐罷免案各投開票所投開票結果表",
      "district": "東區",
      "village": "豐功里",
      "polling_station": "60",
      "agree_votes": 322,
      "disagree_votes": 407,
      "valid_votes": 729,
      "invalid_votes": 4,
      "total_voters": 733,
      "ballots_not_cast": 0,
      "ballots_issued": 733,
      "unused_ballots": 443,
      "eligible_voters": 1176,
      "turnout_rate": 62.33
    },
    {
      "recall_case": "第11屆立法委員(新竹市選舉區)鄭正鈐罷免案各投開票所投開票結果表",
      "district": "東區",
      "village": "豐功里",
      "polling_station": "61",
      "agree_votes": 150,
      "disagree_votes": 325,
      "valid_votes": 475,
      "invalid_votes": 0,
      "total_voters": 475,
      "ballots_not_cast": 0,
      "ballots_issued": 475,
      "unused_ballots": 364,
      "eligible_voters": 839,
      "turnout_rate": 56.62
    },
    {
      "recall_case": "第11屆立法委員(新竹市選舉區)鄭正鈐罷免案各投開票所投開票結果表",
      "district": "東區",
      "village": "豐功里",
      "polling_station": "62",
      "agree_votes": 260,
      "disagree_votes": 399,
      "valid_votes": 659,
      "invalid_votes": 7,
      "total_voters": 666,
      "ballots_not_cast": 0,
      "ballots_issued": 666,
      "unused_ballots": 415,
      "eligible_voters": 1081,
      "turnout_rate": 61.61
    },
    {
      "recall_case": "第11屆立法委員(新竹市選舉區)鄭正鈐罷免案各投開票所投開票結果表",
      "district": "東區",
      "village": "豐功里",
      "polling_station": "63",
      "agree_votes": 281,
      "disagree_votes": 446,
      "valid_votes": 727,
      "invalid_votes": 4,
      "total_voters": 731,
      "ballots_not_cast": 0,
      "ballots_issued": 731,
      "unused_ballots": 422,
      "eligible_voters": 1153,
      "turnout_rate": 63.4
    },
    {
      "recall_case": "新竹市第11屆市長高虹安罷免案在新竹市各投開票所投開票結果表",
      "district": "東區",
      "village": "豐功里",
      "polling_station": "60",
      "agree_votes": 311,
      "disagree_votes": 419,
      "valid_votes": 730,
      "invalid_votes": 5,
      "total_voters": 735,
      "ballots_not_cast": 0,
      "ballots_issued": 735,
      "unused_ballots": 444,
      "eligible_voters": 1179,
      "turnout_rate": 62.34
    },
    {
      "recall_case": "新竹市第11屆市長高虹安罷免案在新竹市各投開票所投開票結果表",
      "district": "東區",
      "village": "豐功里",
      "polling_station": "61",
      "agree_votes": 151,
      "disagree_votes": 328,
      "valid_votes": 479,
      "invalid_votes": 1,
      "total_voters": 480,
      "ballots_not_cast": 0,
      "ballots_issued": 480,
      "unused_ballots": 376,
      "eligible_voters": 856,
      "turnout_rate": 56.07
    },
    {
      "recall_case": "新竹市第11屆市長高虹安罷免案在新竹市各投開票所投開票結果表",
      "district": "東區",
      "village": "豐功里",
      "polling_station": "62",
      "agree_votes": 251,
      "disagree_votes": 406,
      "valid_votes": 657,
      "invalid_votes": 9,
      "total_voters": 666,
      "ballots_not_cast": 0,
      "ballots_issued": 666,
      "unused_ballots": 420,
      "eligible_voters": 1086,
      "turnout_rate": 61.33
    },
    {
      "recall_case": "新竹市第11屆市長高虹安罷免案在新竹市各投開票所投開票結果表",
      "district": "東區",
      "village": "豐功里",
      "polling_station": "63",
      "agree_votes": 271,
      "disagree_votes": 457,
      "valid_votes": 728,
      "invalid_votes": 3,
      "total_voters": 731,
      "ballots_not_cast": 0,
      "ballots_issued": 731,
      "unused_ballots": 423,
      "eligible_voters": 1154,
      "turnout_rate": 63.34
    }
  ],
  "VILLCODE": "10018010024",
  "COUNTYCODE": "10018",
  "TOWNCODE": "10018010",
  "COUNTYNAME": "新竹市",
  "TOWNNAME": "東區",
  "VILLNAME": "豐功里"
}