{
  "cunli": "大安區_龍泉里",
  "total_records": 3,
  "sum_fields": {
    "agree_votes": 1028,
    "disagree_votes": 1167,
    "valid_votes": 2195,
    "invalid_votes": 9,
    "total_voters": 2204,
    "ballots_not_cast": 0,
    "ballots_issued": 2204,
    "unused_ballots": 1612,
    "eligible_voters": 3816,
    "average_turnout_rate": 57.76
  },
  "records": [
    {
      "recall_case": "第11屆立法委員(臺北市第6選舉區)羅智強罷免案各投開票所投開票結果表",
      "district": "大安區",
      "village": "龍泉里",
      "polling_station": "524",
      "agree_votes": 329,
      "disagree_votes": 402,
      "valid_votes": 731,
      "invalid_votes": 3,
      "total_voters": 734,
      "ballots_not_cast": 0,
      "ballots_issued": 734,
      "unused_ballots": 546,
      "eligible_voters": 1280,
      "turnout_rate": 57.34
    },
    {
      "recall_case": "第11屆立法委員(臺北市第6選舉區)羅智強罷免案各投開票所投開票結果表",
      "district": "大安區",
      "village": "龍泉里",
      "polling_station": "525",
      "agree_votes": 355,
      "disagree_votes": 393,
      "valid_votes": 748,
      "invalid_votes": 1,
      "total_voters": 749,
      "ballots_not_cast": 0,
      "ballots_issued": 749,
      "unused_ballots": 547,
      "eligible_voters": 1296,
      "turnout_rate": 57.79
    },
    {
      "recall_case": "第11屆立法委員(臺北市第6選舉區)羅智強罷免案各投開票所投開票結果表",
      "district": "大安區",
      "village": "龍泉里",
      "polling_station": "526",
      "agree_votes": 344,
      "disagree_votes": 372,
      "valid_votes": 716,
      "invalid_votes": 5,
      "total_voters": 721,
      "ballots_not_cast": 0,
      "ballots_issued": 721,
      "unused_ballots": 519,
      "eligible_voters": 1240,
      "turnout_rate": 58.15
    }
  ],
  "VILLCODE": "63000030012",
  "COUNTYCODE": "63000",
  "TOWNCODE": "63000030",
  "COUNTYNAME": "臺北市",
  "TOWNNAME": "大安區",
  "VILLNAME": "龍泉里"
}