{
  "cunli": "南屯區_惠中里",
  "total_records": 5,
  "sum_fields": {
    "agree_votes": 2118,
    "disagree_votes": 2548,
    "valid_votes": 4666,
    "invalid_votes": 21,
    "total_voters": 4687,
    "ballots_not_cast": 0,
    "ballots_issued": 4687,
    "unused_ballots": 3513,
    "eligible_voters": 8200,
    "average_turnout_rate": 57.16
  },
  "records": [
    {
      "recall_case": "第11屆立法委員(臺中市第4選舉區)廖偉翔罷免案各投開票所投開票結果表",
      "district": "南屯區",
      "village": "惠中里",
      "polling_station": "225",
      "agree_votes": 456,
      "disagree_votes": 503,
      "valid_votes": 959,
      "invalid_votes": 2,
      "total_voters": 961,
      "ballots_not_cast": 0,
      "ballots_issued": 961,
      "unused_ballots": 714,
      "eligible_voters": 1675,
      "turnout_rate": 57.37
    },
    {
      "recall_case": "第11屆立法委員(臺中市第4選舉區)廖偉翔罷免案各投開票所投開票結果表",
      "district": "南屯區",
      "village": "惠中里",
      "polling_station": "226",
      "agree_votes": 390,
      "disagree_votes": 522,
      "valid_votes": 912,
      "invalid_votes": 4,
      "total_voters": 916,
      "ballots_not_cast": 0,
      "ballots_issued": 916,
      "unused_ballots": 652,
      "eligible_voters": 1568,
      "turnout_rate": 58.42
    },
    {
      "recall_case": "第11屆立法委員(臺中市第4選舉區)廖偉翔罷免案各投開票所投開票結果表",
      "district": "南屯區",
      "village": "惠中里",
      "polling_station": "227",
      "agree_votes": 420,
      "disagree_votes": 520,
      "valid_votes": 940,
      "invalid_votes": 3,
      "total_voters": 943,
      "ballots_not_cast": 0,
      "ballots_issued": 943,
      "unused_ballots": 808,
      "eligible_voters": 1751,
      "turnout_rate": 53.85
    },
    {
      "recall_case": "第11屆立法委員(臺中市第4選舉區)廖偉翔罷免案各投開票所投開票結果表",
      "district": "南屯區",
      "village": "惠中里",
      "polling_station": "228",
      "agree_votes": 414,
      "disagree_votes": 479,
      "valid_votes": 893,
      "invalid_votes": 8,
      "total_voters": 901,
      "ballots_not_cast": 0,
      "ballots_issued": 901,
      "unused_ballots": 640,
      "eligible_voters": 1541,
      "turnout_rate": 58.47
    },
    {
      "recall_case": "第11屆立法委員(臺中市第4選舉區)廖偉翔罷免案各投開票所投開票結果表",
      "district": "南屯區",
      "village": "惠中里",
      "polling_station": "229",
      "agree_votes": 438,
      "disagree_votes": 524,
      "valid_votes": 962,
      "invalid_votes": 4,
      "total_voters": 966,
      "ballots_not_cast": 0,
      "ballots_issued": 966,
      "unused_ballots": 699,
      "eligible_voters": 1665,
      "turnout_rate": 58.02
    }
  ],
  "VILLCODE": "66000070022",
  "COUNTYCODE": "66000",
  "TOWNCODE": "66000070",
  "COUNTYNAME": "臺中市",
  "TOWNNAME": "南屯區",
  "VILLNAME": "惠中里"
}